MANIFEST.in
README.rst
setup.py
pyimagemonkey/__init__.py
pyimagemonkey/api.py
pyimagemonkey/exceptions.py
pyimagemonkey/utils.py
pyimagemonkey.egg-info/PKG-INFO
pyimagemonkey.egg-info/SOURCES.txt
pyimagemonkey.egg-info/dependency_links.txt
pyimagemonkey.egg-info/requires.txt
pyimagemonkey.egg-info/top_level.txt