Metadata-Version: 1.2
Name: pyimagemonkey
Version: 0.1
Summary: This library is a small wrapper around the ImageMonkey API.
Home-page: https://github.com/bbernhard/imagemonkey-libs
Author: Bernhard
Author-email: schluchti@gmail.com
License: UNKNOWN
Keywords: machine learning,imagemonkey
Platform: UNKNOWN
Requires-Python: >=3.5.0
